{
  "animateLoading": true,
  "borderRadius": "{{appsmith.theme.borderRadius.appBorderRadius}}",
  "bottomRow": 383,
  "displayName": "Text",
  "dynamicBindingPathList": [
    {
      "key": "truncateButtonColor"
    },
    {
      "key": "fontFamily"
    },
    {
      "key": "borderRadius"
    },
    {
      "key": "text"
    }
  ],
  "dynamicHeight": "AUTO_HEIGHT",
  "dynamicTriggerPathList": [],
  "fontFamily": "{{appsmith.theme.fontFamily.appFont}}",
  "fontSize": "1rem",
  "fontStyle": "BOLD",
  "hideCard": false,
  "iconSVG": "/static/media/icon.a47d6d5dbbb718c4dc4b2eb4f218c1b7.svg",
  "isDeprecated": false,
  "isLoading": false,
  "isVisible": true,
  "key": "n1q71ze49v",
  "leftColumn": 1,
  "maxDynamicHeight": 9000,
  "minDynamicHeight": 4,
  "minWidth": 450,
  "mobileBottomRow": 18,
  "mobileLeftColumn": 26,
  "mobileRightColumn": 42,
  "mobileTopRow": 14,
  "originalBottomRow": 383,
  "originalTopRow": 0,
  "overflow": "NONE",
  "parentColumnSpace": 11.796875,
  "parentId": "0",
  "parentRowSpace": 10,
  "renderMode": "CANVAS",
  "responsiveBehavior": "fill",
  "rightColumn": 64,
  "searchTags": [
    "typography",
    "paragraph",
    "label"
  ],
  "shouldTruncate": false,
  "tags": [
    "Suggested",
    "Content"
  ],
  "text": "{{Api1.data}}",
  "textAlign": "LEFT",
  "textColor": "#231F20",
  "topRow": 0,
  "truncateButtonColor": "{{appsmith.theme.colors.primaryColor}}",
  "type": "TEXT_WIDGET",
  "version": 1,
  "widgetId": "dm61hr2v3l",
  "widgetName": "Text1"
}